knitkit_mill/__init__.py
knitkit_mill/main.py
knitkit_mill/version.py
knitkit_mill/assets/cache.tar.gz
knitkit_mill/assets/mill
knitkit_mill-0.1.1.dist-info/METADATA
knitkit_mill-0.1.1.dist-info/WHEEL
knitkit_mill-0.1.1.dist-info/top_level.txt
knitkit_mill-0.1.1.dist-info/RECORD
